awslayer/__init__.py
awslayer/deploy.py
awslayer/helpers.py
awslayer/init.py
awslayer/run.py
awslayer_manager-1.0.14.dist-info/AUTHORS
awslayer_manager-1.0.14.dist-info/LICENSE
awslayer_manager-1.0.14.dist-info/METADATA
awslayer_manager-1.0.14.dist-info/WHEEL
awslayer_manager-1.0.14.dist-info/entry_points.txt
awslayer_manager-1.0.14.dist-info/top_level.txt
awslayer_manager-1.0.14.dist-info/RECORD
