Metadata-Version: 2.1
Name: awslayer-manager
Version: 1.0.14
Summary: A simple, per-project AWS Lambda Layer manager.
Home-page: https://www.example.com
Author: Ramazan Elsunkaev
Author-email: relsunkaev@outlook.com
License: MIT
Platform: UNKNOWN
Classifier: License :: OSI Approved :: MIT License
Classifier: Programming Language :: Python :: 3
Classifier: Programming Language :: Python :: 3.8
Requires-Dist: cursor
